README
setup.py
pysparse/__init__.py
pysparse/setup.py
pysparse/version.py
pysparse.egg-info/PKG-INFO
pysparse.egg-info/SOURCES.txt
pysparse.egg-info/dependency_links.txt
pysparse.egg-info/requires.txt
pysparse.egg-info/top_level.txt
pysparse/direct/__init__.py
pysparse/direct/directSolver.py
pysparse/direct/pysparseSuperLU.py
pysparse/direct/pysparseUmfpack.py
pysparse/direct/setup.py
pysparse/direct/amd/src/amd_1.c
pysparse/direct/amd/src/amd_2.c
pysparse/direct/amd/src/amd_aat.c
pysparse/direct/amd/src/amd_control.c
pysparse/direct/amd/src/amd_defaults.c
pysparse/direct/amd/src/amd_dump.c
pysparse/direct/amd/src/amd_info.c
pysparse/direct/amd/src/amd_order.c
pysparse/direct/amd/src/amd_post_tree.c
pysparse/direct/amd/src/amd_postorder.c
pysparse/direct/amd/src/amd_valid.c
pysparse/direct/src/superlumodule.c
pysparse/direct/src/umfpackmodule.c
pysparse/direct/superlu/src/colamd.c
pysparse/direct/superlu/src/dcolumn_bmod.c
pysparse/direct/superlu/src/dcolumn_dfs.c
pysparse/direct/superlu/src/dcomplex.c
pysparse/direct/superlu/src/dcopy_to_ucol.c
pysparse/direct/superlu/src/dgscon.c
pysparse/direct/superlu/src/dgsequ.c
pysparse/direct/superlu/src/dgsrfs.c
pysparse/direct/superlu/src/dgssv.c
pysparse/direct/superlu/src/dgssvx.c
pysparse/direct/superlu/src/dgstrf.c
pysparse/direct/superlu/src/dgstrs.c
pysparse/direct/superlu/src/dlacon.c
pysparse/direct/superlu/src/dlamch.c
pysparse/direct/superlu/src/dlangs.c
pysparse/direct/superlu/src/dlaqgs.c
pysparse/direct/superlu/src/dmemory.c
pysparse/direct/superlu/src/dpanel_bmod.c
pysparse/direct/superlu/src/dpanel_dfs.c
pysparse/direct/superlu/src/dpivotL.c
pysparse/direct/superlu/src/dpivotgrowth.c
pysparse/direct/superlu/src/dpruneL.c
pysparse/direct/superlu/src/dreadhb.c
pysparse/direct/superlu/src/dsnode_bmod.c
pysparse/direct/superlu/src/dsnode_dfs.c
pysparse/direct/superlu/src/dsp_blas2.c
pysparse/direct/superlu/src/dsp_blas3.c
pysparse/direct/superlu/src/dutil.c
pysparse/direct/superlu/src/dzsum1.c
pysparse/direct/superlu/src/get_perm_c.c
pysparse/direct/superlu/src/icmax1.c
pysparse/direct/superlu/src/izmax1.c
pysparse/direct/superlu/src/lsame.c
