Metadata-Version: 1.1
Name: pysparse
Version: 1.3-dev
Summary: Fast sparse matrix library for Python
Home-page: pysparse.sf.net
Author: PySparse Developers
Author-email: {hamsel,d-orban,wd15}@sf.net,
License: BSD-style
Download-URL: sf.net/projects/pysparse
Platform: Windows
Platform: Linux
Platform: Solaris
Platform: Mac OS-X
Platform: Unix
Classifier: Development Status :: 4 - Beta
Classifier: Intended Audience :: Science/Research
Classifier: Intended Audience :: Developers
Classifier: License :: OSI Approved
Classifier: Programming Language :: Python
Classifier: Programming Language :: C
Classifier: Topic :: Software Development
Classifier: Topic :: Scientific/Engineering
Classifier: Operating System :: Microsoft :: Windows
Classifier: Operating System :: POSIX
Classifier: Operating System :: Unix
Classifier: Operating System :: MacOS :: MacOS X
Classifier: Natural Language :: English
